{
  "generated": "2026-07-10",
  "status": "local-registry-active",
  "source": "os-visualization/system-intelligence/surface-gate-registry.json",
  "summary": "Canonical local registry for Frankly local OS and Lab surfaces, gate state, QA evidence and remaining approvals. 4.0 (2026-07-10): the cockpit is registered as the ONE operating surface; retired v3 pages left the registry (files stay on disk); the two dead blog/ paths now point at journal/. Uploadable website bundles stay allowlisted and separate.",
  "counts": {
    "surfaces": 5,
    "browserQaPassed": 5,
    "publicReady": 0,
    "approvalGated": 5
  },
  "surfaces": [
    {
      "id": "onboarding-entry",
      "name": "Start / onboarding",
      "page": "onboarding.html",
      "state": "local-live",
      "gate": "internal-start-surface",
      "browserQa": "passed",
      "publicUse": "gated",
      "reportFile": "os-visualization/reports/onboarding-entry-gate-2026-07-01.md",
      "evidenceFolder": "os-visualization/evidence/20260701-onboarding-entry-gate-browser-qa/",
      "nextApproval": "Decide sitemap/robots behavior before public use.",
      "anchor": "entry-gate",
      "gateLabelDa": "Kun lokal — kræver dit ja før offentlig"
    },
    {
      "id": "frankly-os-cockpit",
      "name": "Frankly OS Cockpit (4.0)",
      "page": "frankly-os-cockpit.html",
      "state": "local-live",
      "gate": "internal-operating-surface-loopback-only",
      "browserQa": "passed",
      "publicUse": "gated",
      "reportFile": "os-visualization/reports/frankly-lab-40-consolidation-2026-07-10.md",
      "evidenceFolder": "os-visualization/evidence/20260710-frankly-lab-40-consolidation-browser-qa/",
      "nextApproval": "Stays a local operating surface served by cockpit-server.py on 127.0.0.1:8137; any public use requires Jonas approval.",
      "anchor": "cockpit",
      "gateLabelDa": "Kun lokal — kræver dit ja før offentlig"
    },
    {
      "id": "product-clarity-review",
      "name": "Product clarity review gate",
      "page": "frankly-daekningsoverblik.html",
      "state": "review-gated",
      "gate": "product-legal-approval-needed",
      "browserQa": "passed",
      "publicUse": "gated",
      "reportFile": "os-visualization/reports/product-clarity-review-gate-2026-07-01.md",
      "evidenceFolder": "os-visualization/evidence/20260701-product-clarity-review-gate-browser-qa/",
      "nextApproval": "Product/legal must approve terms, exclusions, deductibles and wording.",
      "anchor": "review",
      "gateLabelDa": "Kun lokal — kræver dit ja før offentlig"
    },
    {
      "id": "blog-publishing",
      "name": "Blog draft publishing gate",
      "page": "journal/frankly-blog-index.html",
      "state": "noindex-gated",
      "gate": "publishing-setup-and-product-legal-needed",
      "browserQa": "passed",
      "publicUse": "blocked",
      "reportFile": "os-visualization/reports/blog-publishing-gate-2026-07-01.md",
      "evidenceFolder": "os-visualization/evidence/20260701-blog-publishing-gate-browser-qa/",
      "nextApproval": "Keep blog out of sitemap until source, legal, author/reviewer and schema policy are approved.",
      "anchor": "publish-gate",
      "gateLabelDa": "Blokeret (claims/produkt/legal)"
    },
    {
      "id": "cykelforsikring-article-review",
      "name": "Cykelforsikring article review gate",
      "page": "journal/frankly-blog-05-cyklen.html",
      "state": "noindex-review-gated",
      "gate": "product-claim-source-and-publishing-approval-needed",
      "browserQa": "passed",
      "publicUse": "blocked",
      "reportFile": "os-visualization/reports/article-review-gate-cykelforsikring-2026-07-01.md",
      "evidenceFolder": "os-visualization/evidence/20260701-article-review-gate-browser-qa/",
      "nextApproval": "Frankly bicycle-specific claims, warranty/reklamation sources, author/reviewer, canonical, sitemap and schema remain blocked.",
      "anchor": "article-gate",
      "gateLabelDa": "Blokeret (claims/produkt/legal)"
    }
  ]
}
